<?xml version="1.0" encoding="utf-8"?>
<resources xmlns:xliff="urn:oasis:names:tc:xliff:document:1.2">
    <string name="description_ip_call_action">IP-puhelu <xliff:g id="nameOrNumber" example="John Smith">%1$s</xliff:g></string>
    <string name="select_account">"Valitse tili"</string>
    <string name="all_accounts">"Kaikki tilit"</string>
    <string name="imei_invalid">Virheellinen</string>
    <string name="conf_call_member_list">Jäsenluettelo</string>
    <string name="conf_call_participant_answered">Vastattu</string>
    <string name="conf_call_participant_missed">"Vastaamattomat"</string>
    <string name="can_not_switch_account_during_call">Vaihtaminen ensisijaiseen SIM-korttiin puheluita varten ei onnistu puhelun aikana.</string>
    <string name="can_not_switch_account_temporarily">Vaihtaminen ensisijaiseen SIM-korttiin puheluita varten ei väliaikaisesti onnistu.</string>
</resources>